moonshine/__init__.py
moonshine/model.py
moonshine/transcribe.py
moonshine/version.py
moonshine/assets/beckett.wav
moonshine/assets/tokenizer.json
useful_moonshine-20241016.dist-info/LICENSE
useful_moonshine-20241016.dist-info/METADATA
useful_moonshine-20241016.dist-info/WHEEL
useful_moonshine-20241016.dist-info/top_level.txt
useful_moonshine-20241016.dist-info/RECORD
